a13e/__init__.py
a13e/__main__.py
a13e/api.py
a13e/exception.py
a13e/json_helper.py
a13e/plugin.py
a13e/recognizer.py
a13e/tag.py
a13e/utils.py
a13e/binary/ncm_base64-linux
a13e/binary/ncm_base64-macos
a13e/binary/ncm_base64-win.exe
a13e/plugins/__init__.py
a13e/plugins/neteasecloudmusic/__init__.py
a13e/plugins/neteasecloudmusic/neteasemusic.py
a13e-0.0.1.dist-info/LICENSE
a13e-0.0.1.dist-info/METADATA
a13e-0.0.1.dist-info/WHEEL
a13e-0.0.1.dist-info/entry_points.txt
a13e-0.0.1.dist-info/top_level.txt
a13e-0.0.1.dist-info/RECORD
