Metadata-Version: 2.1
Name: a13e
Version: 0.0.1
Summary: Simple and extensible audio recognition package.
Author-email: Nattsu0514 <nattsu0514@outlook.com>
License: MIT License
Project-URL: Homepage, https://github.com/Nattsu0514/a13e
Classifier: Programming Language :: Python :: 3.8
Classifier: Programming Language :: Python :: 3.9
Classifier: Programming Language :: Python :: 3.10
Classifier: Programming Language :: Python :: 3.11
Classifier: License :: OSI Approved :: MIT License
Classifier: Operating System :: Microsoft :: Windows
Classifier: Operating System :: MacOS
Classifier: Operating System :: POSIX :: Linux
Requires-Python: >=3.8
License-File: LICENSE
Requires-Dist: eyed3 (>=0.9.7)
Requires-Dist: requests (>=2.28.1)
Requires-Dist: typing-extensions (>=4.4.0) ; python_version < "3.10"
Requires-Dist: importlib-resources ; python_version < "3.9"
